tewi/__init__.py
tewi/app.py
tewi/app.tcss
tewi/config.py
tewi/version.py
tewi/search/__init__.py
tewi/search/base.py
tewi/search/manager.py
tewi/search/models.py
tewi/search/util.py
tewi/search/providers/__init__.py
tewi/search/providers/bitmagnet.py
tewi/search/providers/jackett.py
tewi/search/providers/nyaa.py
tewi/search/providers/prowlarr.py
tewi/search/providers/torrentscsv.py
tewi/search/providers/torrentz2.py
tewi/search/providers/tpb.py
tewi/search/providers/yts.py
tewi/torrent/base.py
tewi/torrent/factory.py
tewi/torrent/models.py
tewi/torrent/util.py
tewi/torrent/clients/deluge.py
tewi/torrent/clients/qbittorrent.py
tewi/torrent/clients/transmission.py
tewi/ui/messages.py
tewi/ui/models.py
tewi/ui/util.py
tewi/ui/dialog/__init__.py
tewi/ui/dialog/confirm.py
tewi/ui/dialog/help.py
tewi/ui/dialog/preferences.py
tewi/ui/dialog/statistics.py
tewi/ui/dialog/search/__init__.py
tewi/ui/dialog/search/details.py
tewi/ui/dialog/search/query.py
tewi/ui/dialog/torrent/add.py
tewi/ui/dialog/torrent/category.py
tewi/ui/dialog/torrent/edit.py
tewi/ui/dialog/torrent/filter.py
tewi/ui/dialog/torrent/label.py
tewi/ui/dialog/torrent/search.py
tewi/ui/dialog/torrent/sort.py
tewi/ui/panel/details.py
tewi/ui/panel/info.py
tewi/ui/panel/listview.py
tewi/ui/panel/state.py
tewi/ui/panel/websearch.py
tewi/ui/widget/common.py
tewi/ui/widget/torrent_item.py
tewi/util/__init__.py
tewi/util/clipboard.py
tewi/util/debug.py
tewi/util/geoip.py
tewi/util/log.py
tewi/util/misc.py
tewi_transmission-2.3.1.dist-info/licenses/LICENSE.txt
tewi_transmission-2.3.1.dist-info/METADATA
tewi_transmission-2.3.1.dist-info/WHEEL
tewi_transmission-2.3.1.dist-info/entry_points.txt
tewi_transmission-2.3.1.dist-info/top_level.txt
tewi_transmission-2.3.1.dist-info/RECORD
